napari_adaptive_painting/__init__.py
napari_adaptive_painting/_version.py
napari_adaptive_painting/_widget.py
napari_adaptive_painting/napari.yaml
napari_adaptive_painting-0.0.3.dist-info/licenses/LICENSE
napari_adaptive_painting-0.0.3.dist-info/METADATA
napari_adaptive_painting-0.0.3.dist-info/WHEEL
napari_adaptive_painting-0.0.3.dist-info/entry_points.txt
napari_adaptive_painting-0.0.3.dist-info/top_level.txt
napari_adaptive_painting-0.0.3.dist-info/RECORD
