Metadata-Version: 2.4
Name: napari-adaptive-painting
Version: 0.0.3
Summary: Propagate label annotations in Napari.
Author-email: Mallory Wittwer <mallory.wittwer@epfl.ch>
License: Copyright (c) 2023, Mallory Wittwer
Project-URL: homepage, https://github.com/EPFL-Center-for-Imaging/napari-adaptive-painting
Project-URL: repository, https://github.com/EPFL-Center-for-Imaging/napari-adaptive-painting
Classifier: Development Status :: 2 - Pre-Alpha
Classifier: License :: OSI Approved :: BSD License
Classifier: Programming Language :: Python :: 3
Classifier: Programming Language :: Python :: 3.9
Classifier: Topic :: Scientific/Engineering :: Image Processing
Requires-Python: >=3.9
License-File: LICENSE
Requires-Dist: napari[all]>=0.4.16
Requires-Dist: qtpy
Requires-Dist: numpy
Requires-Dist: scipy
Requires-Dist: scikit-image
Dynamic: license-file
